README.md
setup.py
grammpy_transforms/ContextFree.py
grammpy_transforms/InverseCommon.py
grammpy_transforms/InverseContextFree.py
grammpy_transforms/Manipulations.py
grammpy_transforms/__init__.py
grammpy_transforms.egg-info/PKG-INFO
grammpy_transforms.egg-info/SOURCES.txt
grammpy_transforms.egg-info/dependency_links.txt
grammpy_transforms.egg-info/requires.txt
grammpy_transforms.egg-info/top_level.txt
grammpy_transforms/ChomskyForm/__init__.py
grammpy_transforms/ChomskyForm/transform_from_chomsky_normal_form.py
grammpy_transforms/ChomskyForm/transform_to_chomsky_normal_form.py
grammpy_transforms/EpsilonRulesRemove/__init__.py
grammpy_transforms/EpsilonRulesRemove/epsilon_rules_restore.py
grammpy_transforms/EpsilonRulesRemove/find_nonterminals_rewritable_to_epsilon.py
grammpy_transforms/EpsilonRulesRemove/remove_rules_with_epsilon.py
grammpy_transforms/NongeneratingSymbolsRemove/__init__.py
grammpy_transforms/NongeneratingSymbolsRemove/remove_nongenerating_nonterminals.py
grammpy_transforms/SplittedRules/__init__.py
grammpy_transforms/SplittedRules/splitted_rules.py
grammpy_transforms/UnitRulesRemove/__init__.py
grammpy_transforms/UnitRulesRemove/find_symbols_reachable_by_unit_rules.py
grammpy_transforms/UnitRulesRemove/remove_unit_rules.py
grammpy_transforms/UnitRulesRemove/unit_rules_restore.py
grammpy_transforms/UnreachableSymbolsRemove/__init__.py
grammpy_transforms/UnreachableSymbolsRemove/remove_unreachable_symbols.py