Metadata-Version: 2.1
Name: grammpy-transforms
Version: 1.2.5
Summary: Set of transformations for grammpy library.
Home-page: https://github.com/PatrikValkovic/grammpy-transforms
Author: Patrik Valkovic
Author-email: patrik.valkovic@hotmail.cz
License: GNU General Public License v3.0
Download-URL: https://github.com/PatrikValkovic/grammpy-transforms/archive/v1.2.5.tar.gz
Platform: UNKNOWN
